CONTRIBUTING.md
MANIFEST.in
README.md
bashbeautify.py
setup.cfg
setup.py
bashbeautify.egg-info/PKG-INFO
bashbeautify.egg-info/SOURCES.txt
bashbeautify.egg-info/dependency_links.txt
bashbeautify.egg-info/entry_points.txt
bashbeautify.egg-info/requires.txt
bashbeautify.egg-info/top_level.txt