Metadata-Version: 1.1
Name: bashbeautify
Version: 0.1.8
Summary: A beautifier for Bash shell scripts written in Python.
Home-page: https://github.com/hermanbergwerf/bashbeautify
Author: Herman Bergwerf
Author-email: hermanbergwerf@gmail.com
License: GPLv2
Keywords: automation,bash,format,beautify
Platform: UNKNOWN
Classifier: Environment :: Console
Classifier: Intended Audience :: Developers
